s3nb/__init__.py
s3nb/ipy2.py
s3nb/ipy3.py
s3nb-0.0.5.dist-info/DESCRIPTION.rst
s3nb-0.0.5.dist-info/METADATA
s3nb-0.0.5.dist-info/metadata.json
s3nb-0.0.5.dist-info/RECORD
s3nb-0.0.5.dist-info/top_level.txt
s3nb-0.0.5.dist-info/WHEEL
