Metadata-Version: 2.0
Name: s3nb
Version: 0.0.5
Summary: s3 backed notebook manager for ipython 2.0+
Home-page: https://github.com/monetate/s3nb
Author: Monetate Inc.
Author-email: graphaelli@monetate.com
License: Python
Keywords: ipython
Platform: any
Classifier: Development Status :: 4 - Beta
Classifier: Intended Audience :: Developers
Classifier: Operating System :: OS Independent
Classifier: Programming Language :: Python
Requires-Dist: ipython[notebook] (>=2.0)
Requires-Dist: boto
